pdtypes/__init__.py
pdtypes/formatters.py
pdtypes/groupby.py
pdtypes/patching.py
pdtypes-0.3.0.dist-info/METADATA
pdtypes-0.3.0.dist-info/WHEEL
pdtypes-0.3.0.dist-info/licenses/LICENSE
pdtypes-0.3.0.dist-info/RECORD
