Metadata-Version: 2.4
Name: pdtypes
Version: 0.3.0
Summary: Show data types for pandas data frames in terminal and notebooks
License: BSD 3-Clause
License-File: LICENSE
Author: pwwang
Author-email: pwwang@pwwang.com
Requires-Python: >=3.8,<4.0
Classifier: License :: Other/Proprietary License
Classifier: Programming Language :: Python :: 3
Classifier: Programming Language :: Python :: 3.8
Classifier: Programming Language :: Python :: 3.9
Classifier: Programming Language :: Python :: 3.10
Classifier: Programming Language :: Python :: 3.11
Classifier: Programming Language :: Python :: 3.12
Classifier: Programming Language :: Python :: 3.13
Classifier: Programming Language :: Python :: 3.14
Requires-Dist: pandas (==2.0.*) ; python_version < "3.9"
Requires-Dist: pandas (>=2.1) ; python_version >= "3.11"
Requires-Dist: pandas (>=2.1,<3) ; python_version >= "3.9" and python_version < "3.11"
Project-URL: Homepage, https://github.com/pwwang/pdtypes
Project-URL: Repository, https://github.com/pwwang/pdtypes
